deep_font-0.0.0.dist-info/licenses/LICENSE
deepfont/__init__.py
deep_font-0.0.0.dist-info/METADATA
deep_font-0.0.0.dist-info/WHEEL
deep_font-0.0.0.dist-info/top_level.txt
deep_font-0.0.0.dist-info/RECORD
